flask_exchange/__init__.py
flask_exchange/exchange.py
flask_exchange/extended.py
flask_exchange/item_class.py
Flask_Exchange-0.0.2.dist-info/LICENSE
Flask_Exchange-0.0.2.dist-info/METADATA
Flask_Exchange-0.0.2.dist-info/WHEEL
Flask_Exchange-0.0.2.dist-info/top_level.txt
Flask_Exchange-0.0.2.dist-info/RECORD
