Metadata-Version: 2.1
Name: Flask-Exchange
Version: 0.0.2
Summary: Exchange support for Flask using ExchangeLib.
Home-page: https://github.com/jscurtu/flask-exchange
Author: Jason Scurtu
Author-email: jscurtu@gmail.com
License: MIT
Platform: UNKNOWN
Classifier: Framework :: Flask
Classifier: Topic :: Office/Business :: Groupware
Classifier: License :: OSI Approved :: MIT License
Classifier: Development Status :: 5 - Production/Stable
Classifier: Intended Audience :: Developers
Classifier: Natural Language :: English
Classifier: Operating System :: OS Independent
Classifier: Programming Language :: Python :: 3 :: Only
Classifier: Programming Language :: Python :: 3
Classifier: Programming Language :: Python :: 3.3
Classifier: Programming Language :: Python :: 3.4
Classifier: Programming Language :: Python :: 3.5
Classifier: Programming Language :: Python :: 3.6
Classifier: Programming Language :: Python :: 3.7
Classifier: Programming Language :: Python :: Implementation :: CPython
Classifier: Programming Language :: Python :: Implementation :: PyPy
Requires-Python: >=3.6.0
Requires-Dist: flask (>=0.10.1)
Requires-Dist: exchangelib (>=1.12.0)
Requires-Dist: urllib3
